omkarbhosale_upi_qr/__init__.py
omkarbhosale_upi_qr/generator.py
omkarbhosale_upi_qr-1.1.0.dist-info/METADATA
omkarbhosale_upi_qr-1.1.0.dist-info/WHEEL
omkarbhosale_upi_qr-1.1.0.dist-info/top_level.txt
omkarbhosale_upi_qr-1.1.0.dist-info/RECORD
