Metadata-Version: 2.2
Name: omkarbhosale-upi-qr
Version: 1.1.0
Summary: Generate UPI QR codes with specified amounts
Home-page: https://github.com/0mkarBhosale07/python-upi-qr
Author: Omkar Bhosale
Author-email: omkarbhosale5484@email.com
Classifier: Programming Language :: Python :: 3
Classifier: License :: OSI Approved :: MIT License
Classifier: Operating System :: OS Independent
Requires-Python: >=3.6
Requires-Dist: qrcode[pil]>=7.4.2
Dynamic: author
Dynamic: author-email
Dynamic: classifier
Dynamic: description
Dynamic: description-content-type
Dynamic: home-page
Dynamic: requires-dist
Dynamic: requires-python
Dynamic: summary
